mypackage/__init__.py
mypackage/palindrome.py
mypackage_linhtran-0.0.1.dist-info/METADATA
mypackage_linhtran-0.0.1.dist-info/WHEEL
mypackage_linhtran-0.0.1.dist-info/top_level.txt
mypackage_linhtran-0.0.1.dist-info/RECORD
