Metadata-Version: 2.4
Name: mypackage-linhtran
Version: 0.0.1
Summary: Một gói nhỏ để kiểm tra chuỗi palindrome.
Author-email: Linh Tran <author@example.com>
Project-URL: Homepage, https://github.com/pypa/sampleproject
Project-URL: Issues, https://github.com/pypa/sampleproject/issues
Classifier: Programming Language :: Python :: 3
Classifier: License :: OSI Approved :: MIT License
Classifier: Operating System :: OS Independent
Requires-Python: >=3.8
